betterenv.py
betterenv-1.0.0.dist-info/WHEEL
betterenv-1.0.0.dist-info/METADATA
betterenv-1.0.0.dist-info/RECORD
